tagword_crawler/__init__.py
tagword_crawler/crawler.py
tagword_crawler/spider.py
tagword_crawler/ua.py
tagword_crawler-0.2.1.dist-info/LICENSE
tagword_crawler-0.2.1.dist-info/METADATA
tagword_crawler-0.2.1.dist-info/WHEEL
tagword_crawler-0.2.1.dist-info/top_level.txt
tagword_crawler-0.2.1.dist-info/RECORD
