Metadata-Version: 2.1
Name: tagword-crawler
Version: 0.2.1
Summary: a toolkit for cralwer Chinese OTA site data
Home-page: https://github.com/ushiao/tagword-crawler
Author: Kun JIN
Author-email: kun.jin@tagword.cn
License: MIT
Keywords: Spider,Crawler
Platform: UNKNOWN
Classifier: Development Status :: 3 - Alpha
Classifier: Intended Audience :: Developers
Classifier: Topic :: Software Development :: Build Tools
Classifier: License :: OSI Approved :: MIT License
Classifier: Programming Language :: Python :: 3.3
Classifier: Programming Language :: Python :: 3.4
Classifier: Programming Language :: Python :: 3.5
Classifier: Programming Language :: Python :: 3.6
Classifier: Programming Language :: Python :: 3.7
Requires-Dist: bs4 (==0.0.1)
Requires-Dist: requests (==2.23.0)
